DESCRIPTION.rst
MANIFEST.in
README.rst
setup.cfg
setup.py
pydice/__init__.py
pydice/dice.py
pydice/test_dice.py
pydice.egg-info/PKG-INFO
pydice.egg-info/SOURCES.txt
pydice.egg-info/dependency_links.txt
pydice.egg-info/top_level.txt