Metadata-Version: 1.1
Name: pydice
Version: 1.0.1b4
Summary: Tools for simulating dice and die-rolling
Home-page: https://github.com/terryjbiel/pydice
Author: TJ Biel
Author-email: tbiel@med.umich.edu
License: MIT
Keywords: dice die-rolling
Platform: UNKNOWN
Classifier: Development Status :: 3 - Alpha
Classifier: Intended Audience :: Developers
Classifier: Topic :: Games/Entertainment
Classifier: Topic :: Games/Entertainment :: Board Games
Classifier: Topic :: Games/Entertainment :: Role-Playing
Classifier: Topic :: Games/Entertainment :: Turn Based Strategy
Classifier: License :: OSI Approved :: MIT License
Classifier: Programming Language :: Python :: 2.7
